colbert_matryoshka/__init__.py
colbert_matryoshka/model.py
colbert_matryoshka-0.1.5.dist-info/METADATA
colbert_matryoshka-0.1.5.dist-info/WHEEL
colbert_matryoshka-0.1.5.dist-info/RECORD
