Metadata-Version: 2.4
Name: colbert-matryoshka
Version: 0.1.5
Summary: Matryoshka ColBERT: Multi-dimensional ColBERT embeddings with PyLate
Project-URL: Homepage, https://huggingface.co/dragonkue/colbert-ko-0.1b
Project-URL: Repository, https://github.com/dragonkue/colbert-matryoshka
Author: dragonkue
License: Apache-2.0
Keywords: colbert,embeddings,korean,matryoshka,pylate,retrieval
Classifier: Development Status :: 4 - Beta
Classifier: Intended Audience :: Developers
Classifier: Intended Audience :: Science/Research
Classifier: License :: OSI Approved :: Apache Software License
Classifier: Programming Language :: Python :: 3
Classifier: Programming Language :: Python :: 3.8
Classifier: Programming Language :: Python :: 3.9
Classifier: Programming Language :: Python :: 3.10
Classifier: Programming Language :: Python :: 3.11
Classifier: Programming Language :: Python :: 3.12
Classifier: Topic :: Scientific/Engineering :: Artificial Intelligence
Requires-Python: >=3.8
Requires-Dist: pylate>=1.0.0
Requires-Dist: sentence-transformers>=3.0.0
Requires-Dist: transformers>=4.40.0
